{
  "evictions": [],
  "metadata": {
    "generated_at": "2026-04-30T12:56:19Z",
    "count": 0,
    "global_metrics": {
      "total_runs": 100,
      "total_run_time_seconds": 15382.033436536789,
      "total_repo_updates": 6408,
      "previous_total_buckets": 1234,
      "previous_total_recipes": 127570,
      "bucket_velocity": 0,
      "recipe_velocity": 0,
      "total_evictions": 0,
      "total_api_retries": 0,
      "last_run_discover_time": 3.2402944564819336,
      "last_run_update_time": 8.856481552124023,
      "ecosystem_reliability": 88.9,
      "cache_size_mb": 9.542277336120605,
      "total_unique_recipes": 31001,
      "auto_update_percentage": 85.35,
      "official_recipes": 48390,
      "community_recipes": 79180,
      "stale_buckets": 427,
      "shovel_buckets": 25,
      "scoop_buckets": 1209
    }
  }
}
