{
  "trending": [],
  "metadata": {
    "generated_at": "2026-04-26T20:35:31Z",
    "count": 0,
    "global_metrics": {
      "total_runs": 17,
      "total_run_time_seconds": 214.14610838890076,
      "total_repo_updates": 464,
      "previous_total_buckets": 9,
      "previous_total_recipes": 9283,
      "bucket_velocity": 0,
      "recipe_velocity": 0,
      "total_evictions": 0,
      "total_api_retries": 0,
      "last_run_discover_time": 2.807070016860962,
      "last_run_update_time": 15.536792755126953,
      "ecosystem_reliability": 100.0,
      "cache_size_mb": 0.9194498062133789,
      "total_unique_recipes": 2210,
      "auto_update_percentage": 0.0,
      "official_recipes": 5946,
      "community_recipes": 3337,
      "stale_buckets": 2,
      "shovel_buckets": 0,
      "scoop_buckets": 9
    }
  }
}
